{"pageLoadProgressBar_status":"","pageLoadProgressBar_color":"#2fb5d2","global_themeFont":"roboto","global_basicColor":"#acdffc","global_bodyBackground":"#ffffff","global_link":"#a9abb8","global_linkHover":"#008bff","global_basicfontcolor":"#555555","global_basicfontsize":"13px","global_pfontsize":"13px","global_showquickview":"1","global_quickviewbackground":"#ffffff","h1h6_themeFontH":"raleway","h1h6_h1h5Color":"#010101","h1h6_h1FontSize":"40px","h1h6_h2FontSize":"40px","h1h6_h3h4FontSize":"16px","h1h6_h5FontSize":"13px","h1h6_h6FontSize":"13px","wrapper_breadcrumbBackground":"#ffffff","newslet_background":"#f5f5f5","otherpage_background":"#fff","otherpage_paddinginternalpage":"15px","header_navBackground":"#acdffc","header_fontSizeNav":"13px","header_headerBackground":"#ffffff","header_headerlink":"#070707","header_headerlinkHover":"#008bff","topmenu_background":"#ffffff","topmenu_menuLinkColor":"#000000","topmenu_menuLinkColorHover":"#008bff","topmenu_fontSize":"13px","topmenu_stickyMenu":"1","footer_footerBackground":"#4c4c52","footer_footertitels":"#ffffff","footer_footerlink":"#ffffff","footer_footerlinkHover":"#9fdcfe","copyright_copyrightBackground":"#28282c","copyright_showcopyright":"1","product_productImageChange":"hover","product_backgroundMiniature":"#fff","product_titleCatalogColor":"#010101","product_titleCatalogFontSize":"13px","product_titleFontSize":"40px","product_priceColor":"#010101","product_priceFontSize":"14px","product_oldPriceColor":"#a7a7a7","product_oldPriceFontSize":"14px","product_borderImageCatalog":"0","product_borderImageColorCatalog":"","product_backgroundOnlineOnly":"#ebebeb","product_colorOnlineOnly":"#000000","product_backgroundOnSale":"#ff5357","product_colorOnSale":"#ffffff","product_backgroundNew":"#0077d6","product_colorNew":"#ffffff","product_backgroundSale":"#070707","product_colorSale":"#ffffff","product_backgroundTabs":"#ffffff","product_slideronproductpage":"1","product_addtocart":"without","product_shortdescription":"","product_shortdescriptionlength":"65","segmentedviewsettinds_imagelimit":"5","segmentedviewsettinds_linecolor":"#e8e8e8","segmentedviewsettinds_activelinecolor":"#1cb1ff","segmentedviewsettinds_textcolorsh":"#000000","segmentedviewsettinds_textonlastimg":"1","categoryPage_backgroundleftcolumn":"","categoryPage_leftcolumnpadding":"15px","categoryPage_facetedsearch":"standard","categorydescription_showCategoryDescription":"1","categorydescription_backgrounddescription":"","categorydescription_paddingdescription":"0px","shoppingCart_sidebarCart":"1","shoppingCart_fontsizegsc":"24px","shoppingCart_backgroundsc":"#ffffff","shoppingCart_backgroun2dsc":"#ffffff","shoppingCart_paddingsc":"0px","shoppingCart_backgroundsc2":"#ffffff","shoppingCart_paddingsc2":"0px","orderpage_backgroundorder":"#ffffff","orderpage_paddingorder":"15px","homeSlider_sliderFont":"raleway","homeSlider_titleColor":"#070707","homeSlider_TitleFontSize":"40px","homeSlider_descriptionColor":"#555555","homeSlider_descriptionFontSize":"13px","buttons_backgroundButton":"#070707","buttons_backgroundHoverButton":"#1e1e1e","buttons_borderwidthButton":"0px","buttons_bordercolorButton":"#070707","buttons_colorHoverBorder":"#1e1e1e","buttons_ButtonBorderRadius":"40px","buttons_colorButton":"#ffffff","buttons_colorButtonHover":"#ffffff","buttons_buttoneffect":"1"}